_libasyncproxy.cpython-311-powerpc64le-linux-gnu.so
asyncproxy/AsyncProxy.py
asyncproxy/Forwarder.py
asyncproxy/ForwarderFast.py
asyncproxy/TCPProxy.py
asyncproxy/env.py
asyncproxy-1.1.dist-info/METADATA
asyncproxy-1.1.dist-info/WHEEL
asyncproxy-1.1.dist-info/top_level.txt
asyncproxy-1.1.dist-info/RECORD
asyncproxy-1.1.dist-info/licenses/LICENSE
