Metadata-Version: 2.1
Name: asyncproxy
Version: 1.1
Summary: Background TCP proxy for async IO
Home-page: https://github.com/sippy/libasyncproxy.git
Author: Maksym Sobolyev
Author-email: sobomax@sippysoft.com
License: BSD-2-Clause
Classifier: Operating System :: POSIX
Classifier: Programming Language :: C
Classifier: Programming Language :: Python
License-File: LICENSE
